Metadata-Version: 2.1
Name: pydantic_cli_test
Version: 4.4.0a1
Summary: Turn Pydantic defined Data Models into CLI Tools
Home-page: http://github.com/mpkocher/pydantic-cli
Author: M. Kocher
Author-email: "M. Kocher" <michael.kocher@me.com>
License: MIT License
Project-URL: Source Code, http://github.com/mpkocher/pydantic-cli
Classifier: Programming Language :: Python :: 3
Classifier: Programming Language :: Python :: 3.7
Classifier: Programming Language :: Python :: 3.8
Classifier: Programming Language :: Python :: 3.9
Classifier: Programming Language :: Python :: 3.10
Classifier: Programming Language :: Python :: 3.11
Classifier: Programming Language :: Python :: 3.12
Classifier: License :: OSI Approved :: MIT License
Classifier: Operating System :: OS Independent
Classifier: Topic :: Utilities
Classifier: Topic :: Software Development
Classifier: Typing :: Typed
Requires-Python: >=3.7
License-File: LICENSE
Requires-Dist: pydantic >=1.5
Provides-Extra: dev
Requires-Dist: pre-commit >=3.7.0 ; extra == 'dev'
Requires-Dist: mypy >=0.930 ; extra == 'dev'
Requires-Dist: ruff >=0.4.2 ; extra == 'dev'
Provides-Extra: shtab
Requires-Dist: shtap >=1.3.1 ; extra == 'shtab'
Provides-Extra: test
Requires-Dist: pytest >=6.0.1 ; extra == 'test'
Requires-Dist: pytest-cov >=4.0.0 ; extra == 'test'
